yolov2keras/__init__.py
yolov2keras/config.py
yolov2keras/callbacks/__init__.py
yolov2keras/callbacks/mean_average_precision.py
yolov2keras/dataset/__init__.py
yolov2keras/dataset/augmentations.py
yolov2keras/dataset/datasets.py
yolov2keras/dataset/find_anchors.py
yolov2keras/dataset/helper.py
yolov2keras/inference/__init__.py
yolov2keras/inference/decode_yolo_v2.py
yolov2keras/inference/helper.py
yolov2keras/inference/inference.py
yolov2keras/inference/load_model.py
yolov2keras/losses/__init__.py
yolov2keras/losses/losses.py
yolov2keras/metrics/__init__.py
yolov2keras/metrics/metrics.py
yolov2keras/model/__init__.py
yolov2keras/model/utils.py
yolov2keras/model/weights.py
yolov2keras/models/__init__.py
yolov2keras/models/mobilenet.py
yolov2keras/models/models.py
yolov2keras/models/utils.py
yolov2keras/models/yolov2.py
yolov2keras/tests/__init__.py
yolov2keras/tests/test_inference/__init__.py
yolov2keras/tests/test_inference/test_inference.py
yolov2keras/tests/test_utils/__init__.py
yolov2keras/tests/test_utils/test_iou.py
yolov2keras/utils/__init__.py
yolov2keras/utils/io.py
yolov2keras/utils/iou.py
YoloV2Keras-0.0.6.dist-info/METADATA
YoloV2Keras-0.0.6.dist-info/WHEEL
YoloV2Keras-0.0.6.dist-info/top_level.txt
YoloV2Keras-0.0.6.dist-info/RECORD
