Metadata-Version: 2.1
Name: YoloV2Keras
Version: 0.0.6
Summary: Yolo v2 library
Author: Anuj Panthri
Author-email: panthrianuj@gmail.com
Requires-Python: >=3.7
Requires-Dist: albumentations ==1.3.1
Requires-Dist: appdirs ==1.4.4
Requires-Dist: gradio ==3.45.2
Requires-Dist: matplotlib ==3.7.2
Requires-Dist: numpy ==1.24.3
Requires-Dist: opencv-python-headless ==4.8.0.76
Requires-Dist: pytest ==7.4.2
Requires-Dist: scikit-learn ==1.3.1
Requires-Dist: tensorflow ==2.14.0
Requires-Dist: tqdm ==4.66.1
Requires-Dist: wget ==3.2
